spe/__init__.py
spe/loadspe.py
spens/__init__.py
spens/loadspe.py
spens-1.0.0.dist-info/LICENSE
spens-1.0.0.dist-info/METADATA
spens-1.0.0.dist-info/WHEEL
spens-1.0.0.dist-info/top_level.txt
spens-1.0.0.dist-info/RECORD
