Metadata-Version: 2.1
Name: spens
Version: 1.0.0
Summary: Load an ascii .spe file as a numpy array.
Home-page: https://github.com/agdelma/spe
Author: Adrian Del Maestro
Author-email: adrian@delmaestro.org
License: MIT
Platform: UNKNOWN
Classifier: License :: OSI Approved :: MIT License
Classifier: Programming Language :: Python :: 3.6
Classifier: Programming Language :: Python :: 3.7
Classifier: Topic :: Scientific/Engineering :: Physics
Requires-Python: >=3.6
Requires-Dist: numpy
